{
    "nome": "Arma Elemental",
    "name": "Elemental Weapon",
    "nivel": 3,
    "escola": "elemental",
    "ritual": false,
    "elementos": [
        "água",
        "terra",
        "fogo",
        "ar",
        "luz",
        "sombras",
        "relâmpago",
        "metal",
        "veneno"
    ],
    "tempo_conjuracao": "1 ação bônus",
    "alcance_area": "toque",
    "componentes": "VS",
    "mana": 1400,
    "mana_adicional": "10 por minuto",
    "duracao": "concentração, até 1 hora",
    "dmg_effect": "elemental",
    "dmg": "1d4",
    "classes": [
        "arqueiro",
        "guerreiro",
        "ladino",
        "mago",
        "monge"
    ],
    "tags": [
        "buff",
        "dano",
        "toque",
        "arma"
    ],
    "descricao": "A nonmagical weapon you touch becomes a magic weapon. For the duration, the weapon has a +1 bonus to attack rolls and deals an extra 1d4 elemental damage.\n\t**Enhance Spell** Spending 7000 extra mana, the bonus attack rolls increases to +2 and the extra damage increases to 2d4. Spending 50000 extra mana (i.e. 58400 MP), the bonus attack rolls increases +3 and the extra damage increases to 4d4.",
    "source": "LDJ"
}
