{
    "nome": "Lâmina da Chama Esverdeada",
    "name": "Green-Flame Blade",
    "nivel": 0,
    "escola": "elemental",
    "ritual": false,
    "elementos": [
        "água",
        "terra",
        "fogo",
        "ar",
        "luz",
        "sombras",
        "relâmpago",
        "metal"
    ],
    "tempo_conjuracao": "1 ação",
    "alcance_area": "pessoal",
    "componentes": "SM (uma arma marcial corpo-a-corpo)",
    "mana": 50,
    "duracao": "instantânea",
    "attack_save": "corpo-a-corpo",
    "dmg_effect": "elemental",
    "dmg": "mod",
    "classes": [
        "clérigo",
        "paladino",
        "mago",
        "bruxo",
        "feiticeiro",
        "ladino",
        "guerreiro",
        "monge"
    ],
    "tags": [
        "dano",
        "corpo-a-corpo",
        "arma"
    ],
    "descricao": "Um texto longo pra k7 aqui",
    "source": "LDJ"
}
